README.rst
setup.cfg
setup.py
hops/__init__.py
hops/constants.py
hops/exceptions.py
hops/featurestore.py
hops/job.py
hops/util.py
hops/version.py
hops/featurestore_impl/__init__.py
hops/featurestore_impl/core.py
hops/featurestore_impl/online_featurestore.py
hops/featurestore_impl/dao/__init__.py
hops/featurestore_impl/dao/common/__init__.py
hops/featurestore_impl/dao/common/featurestore_entity.py
hops/featurestore_impl/dao/common/featurestore_metadata.py
hops/featurestore_impl/dao/datasets/__init__.py
hops/featurestore_impl/dao/datasets/training_dataset.py
hops/featurestore_impl/dao/featuregroups/__init__.py
hops/featurestore_impl/dao/featuregroups/cached_featuregroup.py
hops/featurestore_impl/dao/featuregroups/featuregroup.py
hops/featurestore_impl/dao/featuregroups/on_demand_featuregroup.py
hops/featurestore_impl/dao/featuregroups/online_featuregroup.py
hops/featurestore_impl/dao/features/__init__.py
hops/featurestore_impl/dao/features/feature.py
hops/featurestore_impl/dao/features/training_dataset_feature.py
hops/featurestore_impl/dao/featurestore/__init__.py
hops/featurestore_impl/dao/featurestore/featurestore.py
hops/featurestore_impl/dao/settings/__init__.py
hops/featurestore_impl/dao/settings/featurestore_settings.py
hops/featurestore_impl/dao/stats/__init__.py
hops/featurestore_impl/dao/stats/cluster.py
hops/featurestore_impl/dao/stats/cluster_analysis.py
hops/featurestore_impl/dao/stats/correlation_matrix.py
hops/featurestore_impl/dao/stats/correlation_value.py
hops/featurestore_impl/dao/stats/datapoint.py
hops/featurestore_impl/dao/stats/descriptive_stats.py
hops/featurestore_impl/dao/stats/descriptive_stats_metric_value.py
hops/featurestore_impl/dao/stats/descriptive_stats_metric_values.py
hops/featurestore_impl/dao/stats/feature_correlation.py
hops/featurestore_impl/dao/stats/feature_histogram.py
hops/featurestore_impl/dao/stats/feature_histograms.py
hops/featurestore_impl/dao/stats/histogram_bin.py
hops/featurestore_impl/dao/stats/statistics.py
hopsworks_cloud_sdk.egg-info/PKG-INFO
hopsworks_cloud_sdk.egg-info/SOURCES.txt
hopsworks_cloud_sdk.egg-info/dependency_links.txt
hopsworks_cloud_sdk.egg-info/requires.txt
hopsworks_cloud_sdk.egg-info/top_level.txt