Metadata-Version: 2.1
Name: hopsworks-cloud-sdk
Version: 2.0.0.2
Summary: An SDK to integrate cloud solutions such as SageMaker and Databricks with Hopsworks.
Home-page: https://github.com/logicalclocks/hopsworks-cloud-sdk
Author: Steffen Grohsschmiedt
Author-email: steffen@logicalclocks.com
License: Apache License 2.0
Download-URL: http://snurran.sics.se/hops/hopsworks-cloud-sdk/hops-2.0.0.2.tar.gz
Keywords: Hopsworks,SageMaker,Databricks
Platform: UNKNOWN
Classifier: Development Status :: 5 - Production/Stable
Classifier: Topic :: Utilities
Classifier: License :: OSI Approved :: Apache Software License
Classifier: Programming Language :: Python :: 3
Provides-Extra: docs
Provides-Extra: test
Provides-Extra: plotting
